instagram/__init__.py
instagram/constants.py
instagram/instagram.py
instagram/main.py
instagram/utils.py
instagram/version.py
instagram_story-1.3.2.dist-info/LICENSE
instagram_story-1.3.2.dist-info/METADATA
instagram_story-1.3.2.dist-info/WHEEL
instagram_story-1.3.2.dist-info/entry_points.txt
instagram_story-1.3.2.dist-info/top_level.txt
instagram_story-1.3.2.dist-info/RECORD
