Metadata-Version: 2.1
Name: instagram-story
Version: 1.3.2
Summary: Instagram Story downloader
Home-page: https://github.com/skyme5/instagram-story
Author: Aakash Gajjar
Author-email: skyme5@gmx.com
License: MIT license
Keywords: instagram story
Platform: UNKNOWN
Classifier: Programming Language :: Python :: 3
Classifier: License :: OSI Approved :: MIT License
Classifier: Operating System :: OS Independent
Requires-Python: >=3.6
Requires-Dist: jsonschema (>=3.1.1)
Requires-Dist: loguru (>=0.2.5)
Requires-Dist: requests (>=2.22.0)
Requires-Dist: tqdm (>=4.32.1)
